Metadata-Version: 1.0
Name: Dsbn-probabilities
Version: 0.1
Summary: Dsbn_probabilities
Home-page: UNKNOWN
Author: UNKNOWN
Author-email: UNKNOWN
License: UNKNOWN
Platform: UNKNOWN
